README.rst
setup.py
PyWireframe/__init__.py
PyWireframe/__main__.py
PyWireframe/engine.py
PyWireframe/render.py
PyWireframe_extended.egg-info/PKG-INFO
PyWireframe_extended.egg-info/SOURCES.txt
PyWireframe_extended.egg-info/dependency_links.txt
PyWireframe_extended.egg-info/top_level.txt