Metadata-Version: 1.1
Name: PyWireframe-extended
Version: 0.5
Summary: This is an extended version of package PyWireframe. Some bugs from the old version have been fixed.
Home-page: https://pypi.org/project/PyWireframe-extended/
Author: Uploader: 七分诚意
Author-email: UNKNOWN
License: UNKNOWN
Keywords: pywireframe,turtle,3d,graphics,绘图
Platform: UNKNOWN
Classifier: Programming Language :: Python :: 3
Classifier: Operating System :: OS Independent
Classifier: Topic :: Education
